mc_dagprop/__init__.py
mc_dagprop/core.py
mc_dagprop/py.typed
mc_dagprop/types.py
mc_dagprop/analytic/__init__.py
mc_dagprop/analytic/_context.py
mc_dagprop/analytic/_pmf.py
mc_dagprop/analytic/_propagator.py
mc_dagprop/analytic/distributions.py
mc_dagprop/monte_carlo/__init__.py
mc_dagprop/monte_carlo/_core.cp312-win_amd64.pyd
mc_dagprop/monte_carlo/_core.cpp
mc_dagprop/monte_carlo/_core.pyi
mc_dagprop-0.7.0.dist-info/licenses/LICENSE
mc_dagprop-0.7.0.dist-info/METADATA
mc_dagprop-0.7.0.dist-info/WHEEL
mc_dagprop-0.7.0.dist-info/top_level.txt
mc_dagprop-0.7.0.dist-info/RECORD
