Metadata-Version: 2.4
Name: mc-dagprop
Version: 0.7.0
Summary: Fast, Monte Carlo DAG propagation simulator with user‑defined delay distributions
Author: Florian Flükiger
Author-email: Florian Flükiger <flfuchs@student.ethz.ch>
License-Expression: MIT
Classifier: Programming Language :: Python :: 3
Requires-Python: >=3.12
License-File: LICENSE
Requires-Dist: numpy>=2.0.0
Requires-Dist: plotly>=6.0.0; extra == "plot"
Dynamic: author
Dynamic: license-file
